MedicalImageProcessing/__init__.py
MedicalImageProcessing/meshing.py
MedicalImageProcessing/rigidregistration.py
MedicalImageProcessing-1.1.dist-info/LICENSE.txt
MedicalImageProcessing-1.1.dist-info/METADATA
MedicalImageProcessing-1.1.dist-info/WHEEL
MedicalImageProcessing-1.1.dist-info/top_level.txt
MedicalImageProcessing-1.1.dist-info/RECORD
