Metadata-Version: 2.1
Name: MedicalImageProcessing
Version: 1.1
Summary: About A variety of image processing techniques designed for medical image use.
Home-page: https://github.com/caleb-oconnor/MedicalImageProcessing
Author: Caleb OConnor
Author-email: csoconnor@mdanderson.org
Classifier: Programming Language :: Python :: 3
Classifier: License :: OSI Approved :: GNU Affero General Public License v3
Requires-Python: >=3.7
License-File: LICENSE.txt
